pipnest/__init__.py
pipnest/exceptions.py
pipnest/interfaces.py
pipnest/pipnest.py
pipnest/project.py
pipnest-0.0.2.dist-info/LICENSE
pipnest-0.0.2.dist-info/METADATA
pipnest-0.0.2.dist-info/WHEEL
pipnest-0.0.2.dist-info/entry_points.txt
pipnest-0.0.2.dist-info/top_level.txt
pipnest-0.0.2.dist-info/RECORD
