Metadata-Version: 2.1
Name: pipnest
Version: 0.0.2
Summary: Distribute your extension module as a pip installable package
Home-page: https://github.com/Helveg/pip-nest
Author: Robin De Schepper
Author-email: robingilbert.deschepper@unipv.it
License: MIT
Keywords: nest-simulator packaging module extension nest pip
Platform: UNKNOWN
Classifier: Intended Audience :: Science/Research
Classifier: License :: OSI Approved :: MIT License
Classifier: Operating System :: OS Independent
Classifier: Programming Language :: Python
Requires-Dist: setuptools
Provides-Extra: dev
Requires-Dist: sphinx ; extra == 'dev'
Requires-Dist: sphinx-rtd-theme (>=0.4.3) ; extra == 'dev'
Requires-Dist: pre-commit ; extra == 'dev'
Requires-Dist: black ; extra == 'dev'
